marioutils/__init__.py
marioutils/azure/__init__.py
marioutils/azure/src/__init__.py
marioutils/azure/src/blob/__init__.py
marioutils/azure/src/blob/baseclass.py
marioutils/azure/src/blob/connString.py
marioutils/azure/src/blob/defautCredential.py
marioutils/azure/src/blob/management.py
marioutils/azure/tests/__init__.py
marioutils/azure/tests/test_defaultCredential.py
marioutils/databasemanagement/__init__.py
marioutils/databasemanagement/src/__init__.py
marioutils/databasemanagement/src/exceptions.py
marioutils/databasemanagement/src/databases/__init__.py
marioutils/databasemanagement/src/databases/baseclass.py
marioutils/databasemanagement/src/databases/manager.py
marioutils/databasemanagement/src/databases/mariadatabase.py
marioutils/databasemanagement/src/databases/msdatabase.py
marioutils/databasemanagement/tests/__init__.py
marioutils/databasemanagement/tests/test_.py
marioutils/logger/__init__.py
marioutils/logger/src/__init__.py
marioutils/logger/src/logger.py
marioutils/logger/test/__init__.py
marioutils/logger/test/test_logger.py
marioutils-1.2.9.dist-info/METADATA
marioutils-1.2.9.dist-info/WHEEL
marioutils-1.2.9.dist-info/licenses/LICENSE.txt
marioutils-1.2.9.dist-info/RECORD
